setup.py
ExceptionHandler/ExceptionHandler.py
ExceptionHandler/__init__.py
ExceptionHandler.egg-info/PKG-INFO
ExceptionHandler.egg-info/SOURCES.txt
ExceptionHandler.egg-info/dependency_links.txt
ExceptionHandler.egg-info/top_level.txt