Metadata-Version: 1.0
Name: ExceptionHandler
Version: 0.1
Summary: Exception Handler
Home-page: https://github.com/mirbahar/pyException-handler
Author: Mirbahar Nurul Amin
Author-email: rahat.bubt@gmail.com
License: None
Platform: UNKNOWN
